<?xml version="1.0" encoding="UTF-8"?>
<event>
    <name>Collect yours vim configuration files</name>
    <name xml:lang="as">আপোনাৰ vim সংৰূপ নথিপত্ৰসমূহ সংগ্ৰহ কৰক</name>
    <name xml:lang="bg">Събира vim конфигурационните Ви файлове</name>
    <name xml:lang="bn">নিজের প্রয়োজনের vim কনফিগারেশন ফাইল সংগ্রহ করুন</name>
    <name xml:lang="bn_IN">নিজের প্রয়োজনের vim কনফিগারেশন ফাইল সংগ্রহ করুন</name>
    <name xml:lang="cs">Shromáždit uživatelské konfigurační soubory vim</name>
    <name xml:lang="da">Saml dine konfigurationsfiler for vim</name>
    <name xml:lang="de">Sammelt Ihre Vim-Konfigurationsdateien</name>
    <name xml:lang="en_GB">Collect yours vim configuration files</name>
    <name xml:lang="es">Colecta sus archivos de configuración vim</name>
    <name xml:lang="et">Kogu oma vim-i seadetefailid</name>
    <name xml:lang="fi">Kerää käyttäjän vim-asetustiedostot</name>
    <name xml:lang="fr">Collecte vos fichiers de configuration vim</name>
    <name xml:lang="gu">તમારી vim રૂપરેખાંકન ફાઇલોને સંગ્રહો</name>
    <name xml:lang="hi">आपकी vim विन्यास फ़ाइल संग्रह करें</name>
    <name xml:lang="hu">Begyűjti a vim konfigurációs fájlokat</name>
    <name xml:lang="it">Acquisisci i tuoi file di configurazione vim</name>
    <name xml:lang="ja">vim 設定ファイルを収集します</name>
    <name xml:lang="kn">ನಿಮ್ಮ vim ಸಂರಚನಾ ಕಡತಗಳನ್ನು ಸಂಗ್ರಹಿಸಿಟ್ಟುಕೊಳ್ಳಿ</name>
    <name xml:lang="ko">vim 설정 파일을 수집합니다 </name>
    <name xml:lang="lt">Surinkti jūsų vim konfigūracijos failus</name>
    <name xml:lang="ml">നിങ്ങളുടെ vim ക്രമീകരണ ഫയലുകള്‍ ശേഖരിയ്ക്കുക</name>
    <name xml:lang="mr">प्रणालीवरील तुमचे vim संरचना फाइल्स् गोळा करा</name>
    <name xml:lang="nl">Verzamel jouw vim-configuratiebestanden</name>
    <name xml:lang="or">ଆପଣଙ୍କର vim ସଂରଚନା ଫାଇଲଗୁଡ଼ିକୁ ସଂଗ୍ରହ କରନ୍ତୁ</name>
    <name xml:lang="pa">ਆਪਣੀਆਂ vim ਸੰਰਚਨਾ ਫਾਇਲਾਂ ਇਕੱਠੀਆਂ ਕਰੋ</name>
    <name xml:lang="pl">Zbiera pliki konfiguracji użytkownika programu vim</name>
    <name xml:lang="pt">Recolhe os seus ficheiros de configuração vim</name>
    <name xml:lang="pt_BR">Coleta seus arquivos de configuração vim</name>
    <name xml:lang="ru">Сбор пользовательских файлов конфигурации vim</name>
    <name xml:lang="sk">Uložiť konfiguračné súbory editoru vim</name>
    <name xml:lang="sv">Samla in dina vim-konfigurationsfiler</name>
    <name xml:lang="ta">உங்கள் vim கட்டமைப்பு கோப்புகளை சேகரிக்கவும்</name>
    <name xml:lang="te">మీ vim ఆకృతీకరణ ఫైళ్ళను సేకరించును</name>
    <name xml:lang="tr">vim yapılandırma dosyalarını topla</name>
    <name xml:lang="uk">Зібрати ваші файли налаштувань vim</name>
    <name xml:lang="zh_CN">收集您的 vim 配置文件</name>
    <name xml:lang="zh_TW">收集您的 vim 組態檔</name>
    <description>Save .vimrc and .gvimrc from your home directory</description>
    <description xml:lang="as">আপোনাৰ ঘৰ ডাইৰেকটৰিৰ পৰা .vimrc আৰু .gvimrc সঞ্চয় কৰক</description>
    <description xml:lang="bg">Запазва .vimrc и .gvimrc от домашната Ви директория</description>
    <description xml:lang="bn">নিজের ব্যক্তিগত ডিরেক্টরির জন্য .vimrc ও .gvimrc সংরক্ষণ করুন</description>
    <description xml:lang="bn_IN">নিজের ব্যক্তিগত ডিরেক্টরির জন্য .vimrc ও .gvimrc সংরক্ষণ করুন</description>
    <description xml:lang="cs">Ulož ".vimrc" a ".gvimrc" z domácího adresáře</description>
    <description xml:lang="da">Gem .vimrc og .gvimrc fra din hjemmemappe</description>
    <description xml:lang="de">Speichert .vimrc und .gvimrc aus Ihrem Benutzerverzeichnis</description>
    <description xml:lang="en_GB">Save .vimrc and .gvimrc from your home directory</description>
    <description xml:lang="es">Guarda  .vimrc y .gvimrc de su directorio principal</description>
    <description xml:lang="et">Salvesta .vimrc ja .gvimrc failid kodukataloogist</description>
    <description xml:lang="fi">Tallenna kotihakemiston .vimrc- ja .gvimrc-tiedostot</description>
    <description xml:lang="fr">Enregistre .vimrc et .gvimrc depuis votre répertoire de base</description>
    <description xml:lang="gu">તમારી ઘર ડિરેક્ટરીમાંથી .vimrc અને .gvimrc સંગ્રહો</description>
    <description xml:lang="hi">.vimrc और .gvimrc को आपकी घर निर्देशिका से सहेजता है</description>
    <description xml:lang="hu">A .vimrc és .gvimrc fájlok fájlok mentése a /home könyvtárból</description>
    <description xml:lang="it">Salva .vimrc e .gvimrc dalla tua directory home</description>
    <description xml:lang="ja">ホームディレクトリの .vimrc と .gvimrc を保存します</description>
    <description xml:lang="kn">ನಿಮ್ಮ ನೆಲೆ ಕೋಶದಿಂದ .vimrc ಮತ್ತು .gvimrc ಅನ್ನು ಉಳಿಸಿಟ್ಟುಕೊಳ್ಳಿ</description>
    <description xml:lang="ko">홈 디렉토리에서 .vimrc 및 .gvimrc를 저장합니다 </description>
    <description xml:lang="lt">Įrašyti .vimrc ir gvimrc iš jūsų namų katalogo</description>
    <description xml:lang="ml">നിങ്ങളുടെ ആസ്ഥാന ഡയറക്ടറിയില്‍ നിന്നും .vimrc, .gvimrc സൂക്ഷിയ്ക്കുക</description>
    <description xml:lang="mr">होम डिरेक्ट्रीपासून .vimrc व .gvimrc साठवा</description>
    <description xml:lang="nl">Opslaan .vimrc en .gvimrc uit de persoonlijke map</description>
    <description xml:lang="or">.vimrc ଏବଂ .gvimrc କୁ ଆପଣଙ୍କର ମୂଖ୍ୟ ଡିରେକ୍ଟୋରୀରେ ସଂରକ୍ଷଣ କରନ୍ତୁ</description>
    <description xml:lang="pa">ਆਪਣੀ ਘਰੇਲੂ ਡਾਇਰੈਕਟਰੀ ਵਿੱਚੋਂ .vimrc ਅਤੇ .gvimrc ਸੰਭਾਲੋ</description>
    <description xml:lang="pl">Zapisuje pliki .vimrc i .gvimrc z katalogu domowego użytkownika</description>
    <description xml:lang="pt">Grava .vimrc e .gvimrc da sua pasta pessoal</description>
    <description xml:lang="pt_BR">Salva os .vimrc e .gvimrc de seu diretório home.</description>
    <description xml:lang="ru">Получение .vimrc и .gvimrc из домашнего каталога пользователя</description>
    <description xml:lang="sk">Uložiť .vimrc a .gvimrc z domovského adresára</description>
    <description xml:lang="sv">Spara .vimrc och .gvimrc från din hemkatalog</description>
    <description xml:lang="ta">உங்கள் முகப்பு அடைவிலிருந்து .vimrc மற்றும் .gvimrc சேமிக்கவும்</description>
    <description xml:lang="te">మీ హోమ్ డైరెక్టరీనుండి .vimrc మరియు .gvimrc ను దాయును</description>
    <description xml:lang="tr">Ana dizinden .vimrc ve .gvimrc kaydet</description>
    <description xml:lang="uk">Зберегти .vimrc та .gvimrc з вашого домашнього каталогу</description>
    <description xml:lang="zh_CN">保存您主目录中的 .vimrc 和 .gvimrc。</description>
    <description xml:lang="zh_TW">從您的家目錄儲存 .vimrc 與 .gvimrc</description>
    <long-description>Checks if there are .vimrc and .gvimrc in your home directory and saves them as user_vimrc and user_gvimrc, respectively.</long-description>
    <long-description xml:lang="as">আপোনাৰ ঘৰ ডাইৰেকটৰিত .vimrc and .gvimrc আছে নে নীৰিক্ষণ কৰে আৰু সিহতক user_vimrc আৰু user_gvimrc হিচাপে সঞ্চয় কৰে।</long-description>
    <long-description xml:lang="bg">Проверява за наличието на .vimrc и .gvimrc във Вашата домашна директория и ги записва като user_vimrc и user_gvimrc, респективно.</long-description>
    <long-description xml:lang="bn">ব্যবহারকারীর ব্যক্তিগত ডিরেক্টরির মধ্যে .vimrc ও .gvimrc ফাইলগুলি উপস্থিত রয়েছে কিনা তা যাচাই করা হয় ও যথাক্রমে user_vimrc ও user_gvimrc নামে তা সংরক্ষণ করা হয়।</long-description>
    <long-description xml:lang="bn_IN">ব্যবহারকারীর ব্যক্তিগত ডিরেক্টরির মধ্যে .vimrc ও .gvimrc ফাইলগুলি উপস্থিত রয়েছে কিনা তা যাচাই করা হয় ও যথাক্রমে user_vimrc ও user_gvimrc নামে তা সংরক্ষণ করা হয়।</long-description>
    <long-description xml:lang="cs">Zkontroluje existenci souborů ".vimrc" a ".gvimrc" v domácím adresáři a uloží je jako "user_vimrc" resp. "user_gvimrc"</long-description>
    <long-description xml:lang="da">Kontrollér om der er en .vimrc og .gvimrc i din hjemmemappe og gem dem som user_vimrc og user_gvimrc.</long-description>
    <long-description xml:lang="de">Prüft, ob .vimrc und .gvimrc in Ihrem Benutzerverzeichnis vorhanden sind und speichert diese als user_vimrc bzw. user_gvimrc.</long-description>
    <long-description xml:lang="en_GB">Checks if there are .vimrc and .gvimrc in your home directory and saves them as user_vimrc and user_gvimrc, respectively.</long-description>
    <long-description xml:lang="es">Verifica si hay en su directorio principal .vimrc y .gvimrc y los guarda como /etc/vimrc y /etc/gvimrc, respectivamente.</long-description>
    <long-description xml:lang="et">Kontrollib, kassinu kodukataloogis on .vimrc ja .gvimrc faile ja salvestab nad vastavalt user_vimrc ja user_gvimrc.</long-description>
    <long-description xml:lang="fi">Tarkistaa onko kotihakemistossa .vimrc- ja .gvimrc-tiedostot ja tallentaa ne user_vimrc- ja user_gvimrc-nimillä.</long-description>
    <long-description xml:lang="fr">Vérifie si des fichiers .vimrc et .gvimrc se trouvent dans votre répertoire de base et les enregistre respectivement sous user_vimrc and user_gvimrc.</long-description>
    <long-description xml:lang="gu">જો તમારી ઘર ડિરેક્ટરીમાં .vimrc અને .gvimrc છે તો તેને ચકાસે છે અને user_vimrc અને user_gvimrc તરીકે તેઓનો સંગ્રહ કરે છે.</long-description>
    <long-description xml:lang="hi">जाँचें कि क्या .vimrc और .gvimrc आपकी घर निर्देशिका में है और उन्हें बतौर user_vimrc और user_gvimrc क्रमशः सहेजता है.</long-description>
    <long-description xml:lang="hu">Ellenőrzi hogy a .vimrc és .gvimrc fájlok jelen vannak-e az /home könyvtárban és elmenti őket, mint system_vimrc és system_gvimrc.</long-description>
    <long-description xml:lang="it">Controlla la presenza .vimrc e .gvimrc nella directory home archiviandoli come user_vimrc e user_gvimrc.</long-description>
    <long-description xml:lang="ja">ホームディレクトリに .vimrc と .gvimrc があるか確認して、 それぞれを user_vimrc と user_gvimrc として保存します</long-description>
    <long-description xml:lang="kn">ನಿಮ್ಮ ನೆಲೆ ಕೋಶದಲ್ಲಿ .vimrc ಮತ್ತು .gvimrc ಇದೆಯೆ ಎಂದು ಪರೀಕ್ಷಿಸುತ್ತದೆ ಮತ್ತು ಅವನ್ನು ಅನುಕ್ರಮವಾಗಿ user_vimrc ಮತ್ತು user_gvimrcಯಲ್ಲಿ  ಉಳಿಸಿಡುತ್ತದೆ.</long-description>
    <long-description xml:lang="ko">홈 디렉토리에 .vimrc 및 .gvimrc가 있는지 확인하고 이를 각각 user_vimrc 및 user_gvimrc로 저장합니다. </long-description>
    <long-description xml:lang="lt">Patikrina, ar jūsų namų kataloge yra .vimrc ir .gvimrc bei juos įrašo atitinkamai kaip user_vimrc ir user_gvimrc.</long-description>
    <long-description xml:lang="ml">/etc-ല്‍ vimrc, gvimrc ഫയലുകള്‍ ഉണ്ടോ എന്നു് പരിശോധിച്ചു്, അവ user_vimrc, user_gvimrc എന്നിവയായി സൂക്ഷിയ്ക്കുക.</long-description>
    <long-description xml:lang="mr">होम डिरेक्ट्रीत .vimrc व .gvimrc आहे किंवा नाही याची तपासणी करतो व त्यास परस्पररित्या user_vimrc व user_gvimrc म्हणून साठवतो.</long-description>
    <long-description xml:lang="nl">Controleert of er .vimrc en .gvimrc bestanden in de persoonlijke map bestaan en slaat ze op als respectievelijk user_vimrc en user_gvimrc.</long-description>
    <long-description xml:lang="or">ଆପଣଙ୍କର ମୂଖ୍ୟ ଡିରେକ୍ଟୋରୀରେ .vimrc ଏବଂ .gvimrc ଅଛି କି ନାହିଁ ଯାଞ୍ଚ କରିଥାଏ ଏବଂ ସେଗୁଡ଼ିକୁuser_vimrc ଏବଂ user_gvimrc ଭାବରେ ସଂରକ୍ଷଣ କରିଥାଏ।</long-description>
    <long-description xml:lang="pa">ਜਾਂਚੋ ਜੇ .vimrc ਅਤੇ .gvimrc ਤੁਹਾਡੀ ਘਰੇਲੂ ਡਾਇਰੈਕਰੀ ਵਿੱਚ ਹਨ ਅਤੇ user_vimrc ਅਤੇ user_gvimrc, ਤੌਰ ਤੇ ਸੰਭਾਲੋ।</long-description>
    <long-description xml:lang="pl">Sprawdza, czy istnieją pliki .vimrc i .gvimrc w katalogu domowym i zapisuje je jako user_vimrc i user_gvimrc.</long-description>
    <long-description xml:lang="pt">Verifica se existem .vimrc e .gvimrc na sua pasta pessoal e grava-os como user_vimrc e user_gvimrc, respectivamente.</long-description>
    <long-description xml:lang="pt_BR">Verifica se existem .vimrc e .gvimrc em seu diretório home e os salva como user_vimrc e user_gvimrc, respectivamente.</long-description>
    <long-description xml:lang="ru">Поиск  .vimrc и .gvimrc  в домашнем каталоге и их сохранение как user_vimrc и user_gvimrc.</long-description>
    <long-description xml:lang="sk">Kontroluje prítomnosť .vimrc a .gvimrc súborov v domovskom adresári a ukladá ich ako user_vimrc respektíve user_gvimrc.</long-description>
    <long-description xml:lang="sv">Kontrollerar om det finns .vimrc och .gvimrc i din hemkatalog och sparar dem som user_vimrc respektive user_gvimrc.</long-description>
    <long-description xml:lang="ta">vimrc மற்றும் gvimrc உங்கள் முகப்பு அடைவில் இருந்தால் அவற்றை user_vimrc மற்றும் user_gvimrc, முறையே சேமிக்கின்றது.</long-description>
    <long-description xml:lang="te">మీ హోమ్ డైరెక్టరీనందు .vimrc మరియు .gvimrc వున్నాయేమో పరిశీలించును మరియు వాటిని user_vimrc మరియు user_gvimrc గా దాయును.</long-description>
    <long-description xml:lang="tr">Ana dizinde .vimrc ve .gvimrc dosyalarını kontrol et ve onları sırasıyla user_vimrc ve user_gvimrc olarak kaydet.</long-description>
    <long-description xml:lang="uk">Шукає .vimrc і .gvimrc у вашому домашньому каталозі і зберігає їх як user_vimrc і user_gvimrc, відповідно.</long-description>
    <long-description xml:lang="zh_CN">检查在您的主目录中是否有 .vimrc 和 .gvimrc，并将其分别保存为 user_vimrc 和 user_gvimrc。</long-description>
    <long-description xml:lang="zh_TW">檢查您的家目錄是否有 .vimrc 與 .gvimrc，並將它們個別儲存為 user_vimrc 與 user_gvimrc。</long-description>
    <creates-items>user_vimrc,user_gvimrc</creates-items>
    <gui-review-elements>no</gui-review-elements>
</event>